[
  {"title": "Can I email – Features", "url": "https://www.caniemail.com/features", "tags": ["email","compat","reference"], "category": "Email resources"},
  {"title": "Email workshop (hteumeuleu)", "url": "https://github.com/hteumeuleu/email-workshop", "tags": ["email","workshop"], "category": "Email resources"},
  {"title": "Email bugs (hteumeuleu)", "url": "https://github.com/hteumeuleu/email-bugs", "tags": ["email","bugs"], "category": "Email resources"},
  {"title": "Email guidelines (hteumeuleu)", "url": "https://github.com/hteumeuleu/email-guidelines", "tags": ["email","guidelines"], "category": "Email resources"},
  {"title": "Can I email – repository", "url": "https://github.com/hteumeuleu/caniemail", "tags": ["email","compat"], "category": "Email resources"},
  {"title": "Bulletproof Background Images", "url": "https://backgrounds.cm/", "tags": ["email","backgrounds","cm"], "category": "Email resources"},
  {"title": "Bulletproof email buttons", "url": "https://buttons.cm/", "tags": ["email","buttons","cm"], "category": "Email resources"},
  {"title": "CSS Selectors explained", "url": "https://hugogiraudel.github.io/selectors-explained/", "tags": ["css","selectors"], "category": "Articles"},
  {"title": "Litmus – Banning blue links on iOS (update)", "url": "https://www.litmus.com/blog/update-banning-blue-links-on-ios-devices-2/", "tags": ["email","ios","links"], "category": "Email resources"},
  {"title": "Good Email Code (index)", "url": "https://www.goodemailcode.com/", "tags": ["email","patterns"], "category": "Email resources"},
  {"title": "codsen/email-comb", "url": "https://codsen.com/os/email-comb", "tags": ["email","tool","css"], "category": "Tools"},
  {"title": "email-bugs – issue #13", "url": "https://github.com/hteumeuleu/email-bugs/issues/13", "tags": ["email","bugs"], "category": "Email resources"},
  {"title": "email-bugs – issue #16", "url": "https://github.com/hteumeuleu/email-bugs/issues/16", "tags": ["email","bugs"], "category": "Email resources"},
  {"title": "Outlook DPI scaling issues", "url": "https://www.courtneyfantinato.com/correcting-outlook-dpi-scaling-issues/", "tags": ["email","outlook","dpi"], "category": "Email resources"},
  {"title": "EmailComb (light)", "url": "https://emailcomb.com/light", "tags": ["email","tool","minify"], "category": "Tools"},
  {"title": "HTMLCrush (light)", "url": "https://htmlcrush.com/light", "tags": ["html","tool","minify"], "category": "Tools"},
  {"title": "Parcel (useparcel)", "url": "https://useparcel.com/", "tags": ["email","builder","tool"], "category": "Tools"},
  {"title": "Email on Acid (homepage)", "url": "https://www.emailonacid.com/", "tags": ["email","testing"], "category": "Email resources"},
  {"title": "Litmus (homepage)", "url": "https://www.litmus.com/", "tags": ["email","testing"], "category": "Email resources"},
  {"title": "thebetter.email – resources", "url": "https://thebetter.email/resources/", "tags": ["email","resources"], "category": "Email resources"},
  {"title": "Open Doodles", "url": "https://opendoodles.com/", "tags": ["illustrations","assets"], "category": "Design assets"},
  {"title": "Open Peeps", "url": "https://openpeeps.com/", "tags": ["illustrations","assets"], "category": "Design assets"},
  {"title": "Can I email – tests folder", "url": "https://github.com/hteumeuleu/caniemail/tree/main/tests", "tags": ["email","tests","compat"], "category": "Email resources"},
  {"title": "Can I email – repository", "url": "https://github.com/hteumeuleu/caniemail/tree/main", "tags": ["email","compat"], "category": "Email resources"},
  {"title": "HTML Standard – Non‑conforming features", "url": "https://html.spec.whatwg.org/multipage/obsolete.html#non-conforming-features", "tags": ["html","spec","whatwg"], "category": "Specs"},
  {"title": "Litmus – Community Snippets", "url": "https://litmus.com/community/snippets?ref=emailresourc.es", "tags": ["email","litmus","snippets"], "category": "Email resources"},
  {"title": "Awesome Copilot – Chat modes", "url": "https://github.com/github/awesome-copilot/tree/main/chatmodes", "tags": ["copilot","ai"], "category": "Tools"},
  {"title": "MDN – conic-gradient()", "url": "https://developer.mozilla.org/en-US/docs/Web/CSS/gradient/conic-gradient", "tags": ["css","gradients","mdn"], "category": "MDN"},
  {"title": "MDN – linear-gradient()", "url": "https://developer.mozilla.org/en-US/docs/Web/CSS/gradient/linear-gradient", "tags": ["css","gradients","mdn"], "category": "MDN"},
  {"title": "CSS Color 5 – light-dark() spec", "url": "https://drafts.csswg.org/css-color-5/#light-dark", "tags": ["css","color","spec"], "category": "Specs"},
  {"title": "MDN – light-dark()", "url": "https://developer.mozilla.org/en-US/docs/Web/CSS/color_value/light-dark", "tags": ["css","color","mdn"], "category": "MDN"},
  {"title": "MDN – Border-radius generator", "url": "https://developer.mozilla.org/en-US/docs/Web/CSS/CSS_backgrounds_and_borders/Border-radius_generator", "tags": ["css","tool","mdn"], "category": "Tools"},
  {"title": "MDN – border-radius", "url": "https://developer.mozilla.org/en-US/docs/Web/CSS/border-radius", "tags": ["css","borders","mdn"], "category": "MDN"},
  {"title": "MDN – color-interpolation-method", "url": "https://developer.mozilla.org/en-US/docs/Web/CSS/color-interpolation-method", "tags": ["css","color","mdn"], "category": "MDN"},
  {"title": "MDN – Box-shadow generator", "url": "https://developer.mozilla.org/en-US/docs/Web/CSS/CSS_backgrounds_and_borders/Box-shadow_generator", "tags": ["css","tool","mdn"], "category": "Tools"},
  {"title": "Flexplorer – Flexbox visualizer", "url": "https://bennettfeely.com/flexplorer/", "tags": ["css","flexbox","tool"], "category": "Tools"},
  {"title": "MDN – Flexbox basics", "url": "https://developer.mozilla.org/en-US/docs/Web/CSS/CSS_flexible_box_layout/Basic_concepts_of_flexbox", "tags": ["css","flexbox","mdn"], "category": "MDN"},
  {"title": "MDN – HTML img element", "url": "https://developer.mozilla.org/en-US/docs/Web/HTML/Reference/Elements/img", "tags": ["html","mdn","images"], "category": "MDN"},
  {"title": "MDN – HTML button element", "url": "https://developer.mozilla.org/en-US/docs/Web/HTML/Reference/Elements/button", "tags": ["html","mdn"], "category": "MDN"},
  {"title": "MDN – :visited", "url": "https://developer.mozilla.org/en-US/docs/Web/CSS/:visited", "tags": ["css","selectors","mdn"], "category": "MDN"},
  {"title": "HTML – input type=tel", "url": "https://html.spec.whatwg.org/multipage/input.html#telephone-state-(type=tel)", "tags": ["html","spec","whatwg"], "category": "Specs"},
  {"title": "MDN – :link", "url": "https://developer.mozilla.org/en-US/docs/Web/CSS/:link", "tags": ["css","selectors","mdn"], "category": "MDN"},
  {"title": "MDN – HTML a element", "url": "https://developer.mozilla.org/en-US/docs/Web/HTML/Reference/Elements/a", "tags": ["html","mdn","links"], "category": "MDN"},
  {"title": "CSS Selectors – :visited pseudo (spec)", "url": "https://drafts.csswg.org/selectors/#visited-pseudo", "tags": ["css","selectors","spec"], "category": "Specs"},
  {"title": "HTML – :visited selector definition", "url": "https://html.spec.whatwg.org/multipage/semantics-other.html#selector-visited", "tags": ["html","selectors","spec"], "category": "Specs"},
  {"title": "MDN – img: srcset", "url": "https://developer.mozilla.org/en-US/docs/Web/HTML/Reference/Elements/img#srcset", "tags": ["html","images","mdn"], "category": "MDN"},
  {"title": "MDN – Aligning items in flex container", "url": "https://developer.mozilla.org/en-US/docs/Web/CSS/CSS_flexible_box_layout/Aligning_items_in_a_flex_container", "tags": ["css","flexbox","mdn"], "category": "MDN"},
  {"title": "CSS Align – align-items (spec)", "url": "https://drafts.csswg.org/css-align/#align-items-property", "tags": ["css","align","spec"], "category": "Specs"},
  {"title": "MDN – align-content", "url": "https://developer.mozilla.org/en-US/docs/Web/CSS/align-content", "tags": ["css","align","mdn"], "category": "MDN"},
  {"title": "MDN – align-items", "url": "https://developer.mozilla.org/en-US/docs/Web/CSS/align-items", "tags": ["css","align","mdn"], "category": "MDN"},
  {"title": "MDN – align-self", "url": "https://developer.mozilla.org/en-US/docs/Web/CSS/align-self", "tags": ["css","align","mdn"], "category": "MDN"},
  {"title": "MDN – alignment-baseline", "url": "https://developer.mozilla.org/en-US/docs/Web/CSS/alignment-baseline", "tags": ["css","svg","typography","mdn"], "category": "MDN"},
  {"title": "MDN – dominant-baseline", "url": "https://developer.mozilla.org/en-US/docs/Web/CSS/dominant-baseline", "tags": ["css","svg","typography","mdn"], "category": "MDN"},
  {"title": "MDN – column-width", "url": "https://developer.mozilla.org/en-US/docs/Web/CSS/column-width", "tags": ["css","layout","mdn"], "category": "MDN"},
  {"title": "Microsoft – VML fill element gradient", "url": "https://learn.microsoft.com/en-us/windows/win32/vml/web-workshop---how-to-use-vml-on-web-pages-----fill--element#gradient-fill", "tags": ["vml","outlook","legacy"], "category": "Email resources"},
  {"title": "W3C – CSS Images Level 3", "url": "https://www.w3.org/TR/css-images-3/", "tags": ["css","images","spec"], "category": "Specs"},
  {"title": "GitHub.dev workspace link", "url": "https://neglected-spooky-poltergeist-p794pjr7qvjhr4xj.github.dev", "tags": ["codespaces","github.dev"], "category": "Tools"},
  {"title": "W3C – Vector Markup Language NOTE", "url": "https://www.w3.org/TR/NOTE-VML#-toc416858389", "tags": ["vml","spec","legacy"], "category": "Specs"},
  {"title": "email-bugs – issue #135", "url": "https://github.com/hteumeuleu/email-bugs/issues/135", "tags": ["email","bugs","github"], "category": "Email resources"},
  {"title": "caniemail – css-gradients test", "url": "https://github.com/hteumeuleu/caniemail/blob/main/tests/css-gradients.html", "tags": ["email","tests","css"], "category": "Email resources"},
  {"title": "caniemail – css-flexbox test", "url": "https://github.com/hteumeuleu/caniemail/blob/main/tests/css-flexbox.html", "tags": ["email","tests","css"], "category": "Email resources"},
  {"title": "caniemail – css-flex-wrap test", "url": "https://github.com/hteumeuleu/caniemail/blob/main/tests/css-flex-wrap.html", "tags": ["email","tests","css"], "category": "Email resources"},
  {"title": "caniemail – @font-face test", "url": "https://github.com/hteumeuleu/caniemail/blob/main/tests/css-font-face.html", "tags": ["email","tests","fonts"], "category": "Email resources"},
  {"title": "caniemail – light-dark() test", "url": "https://github.com/hteumeuleu/caniemail/blob/main/tests/css-function-light-dark.html", "tags": ["email","tests","color"], "category": "Email resources"},
  {"title": "caniemail – line-height test", "url": "https://github.com/hteumeuleu/caniemail/blob/main/tests/css-line-height.html", "tags": ["email","tests","typography"], "category": "Email resources"},
  {"title": "caniemail – prefers-color-scheme test", "url": "https://github.com/hteumeuleu/caniemail/blob/main/tests/css-media-prefers-color-scheme.html", "tags": ["email","tests","dark-mode"], "category": "Email resources"},
  {"title": "W3C – CSS Images Level 3 (dup)", "url": "https://www.w3.org/TR/css-images-3/", "tags": ["css","images","spec"], "category": "Specs", "notes": "Duplicate provided; kept for completeness."},
  {"title": "CSSWG – ridge-borders color note", "url": "https://github.com/w3c/csswg-drafts/blob/noamr-patch-3/css-borders-4/ridge-borders/color.html", "tags": ["css","borders","spec"], "category": "Specs"},
  {"title": "CSSWG Drafts – css-ruby-1 branch", "url": "https://github.com/w3c/csswg-drafts/tree/noamr-patch-3/css-ruby-1", "tags": ["css","ruby","spec"], "category": "Specs"},
  {"title": "MDN – HTML Reference (index)", "url": "https://developer.mozilla.org/en-US/docs/Web/HTML/Reference", "tags": ["html","mdn"], "category": "MDN"},
  {"title": "HTML – spec introduction background", "url": "https://html.spec.whatwg.org/multipage/introduction.html#background", "tags": ["html","spec"], "category": "Specs"},
  {"title": "caniemail – color-scheme test", "url": "https://github.com/hteumeuleu/caniemail/blob/main/tests/css-color-scheme.html", "tags": ["email","tests","dark-mode"], "category": "Email resources"},
  {"title": "CSSWG Drafts – css-backgrounds-4 branch", "url": "https://github.com/w3c/csswg-drafts/tree/noamr-patch-3/css-backgrounds-4", "tags": ["css","backgrounds","spec"], "category": "Specs"},
  {"title": "CSSWG Drafts – css-backgrounds-3 branch", "url": "https://github.com/w3c/csswg-drafts/tree/noamr-patch-3/css-backgrounds-3", "tags": ["css","backgrounds","spec"], "category": "Specs"},
  {"title": "CSSWG – commit f65d6c…", "url": "https://github.com/w3c/csswg-drafts/commit/f65d6ca7bcad264d2521299caeeebaf664b68acb", "tags": ["css","commits"], "category": "Specs"},
  {"title": "CSSWG – commit 05d9b8…", "url": "https://github.com/w3c/csswg-drafts/commit/05d9b87499c9cde275826612053374af0e694cbd", "tags": ["css","commits"], "category": "Specs"},
  {"title": "CSSWG – commit b66764…", "url": "https://github.com/w3c/csswg-drafts/commit/b667648046860289ec447feddbad987969929ed2", "tags": ["css","commits"], "category": "Specs"},
  {"title": "CSSWG – commit 281749…", "url": "https://github.com/w3c/csswg-drafts/commit/281749be6d18c5c1632b92c633e8b5c51d79e38b", "tags": ["css","commits"], "category": "Specs"},
  {"title": "CSSWG – commit 930a89…", "url": "https://github.com/w3c/csswg-drafts/commit/930a89b5b7c3b0727bd170833fd5465c191d47b1", "tags": ["css","commits"], "category": "Specs"},
  {"title": "CSSWG – commit 830904…", "url": "https://github.com/w3c/csswg-drafts/commit/830904d7e99b778ab97e313feddcd5ed49710af5", "tags": ["css","commits"], "category": "Specs"},
  {"title": "CSSWG – commit 7afea7…", "url": "https://github.com/w3c/csswg-drafts/commit/7afea74ede5f909e0ce7f0308ff4dfa8d7c1f618", "tags": ["css","commits"], "category": "Specs"},
  {"title": "CSSWG – commit 151b22…", "url": "https://github.com/w3c/csswg-drafts/commit/151b22e03a1caaac50bee4583b0339a7562d7f19", "tags": ["css","commits"], "category": "Specs"},
  {"title": "CSSWG – commit cecb9f…", "url": "https://github.com/w3c/csswg-drafts/commit/cecb9fa28675c73a27d5dd979154b28db18a08ce", "tags": ["css","commits"], "category": "Specs"},
  {"title": "CSSWG – commit b554cf…", "url": "https://github.com/w3c/csswg-drafts/commit/b554cf504ba7331b4b8eeae9b9d1c232dfa171c3", "tags": ["css","commits"], "category": "Specs"},
  {"title": "FXTF Drafts (filters/effects WG)", "url": "https://github.com/w3c/fxtf-drafts/", "tags": ["svg","filters","spec"], "category": "Specs"},
  {"title": "CSSWG – commit b2aaa9…", "url": "https://github.com/w3c/csswg-drafts/commit/b2aaa97142a205fe6f79332b9c07e2bf9ad87b7c", "tags": ["css","commits"], "category": "Specs"},
  {"title": "CSS Backgrounds 3 – issues awk", "url": "https://github.com/w3c/csswg-drafts/blob/main/css-backgrounds-3/issues-txt-to-html.awk", "tags": ["css","backgrounds","spec"], "category": "Specs"},
  {"title": "CSS Backgrounds 3 – issues CR 2014", "url": "https://github.com/w3c/csswg-drafts/blob/main/css-backgrounds-3/issues-cr-2014.html", "tags": ["css","backgrounds","spec"], "category": "Specs"},
  {"title": "CSS Backgrounds 3 – transition updated CR 2017", "url": "https://github.com/w3c/csswg-drafts/blob/main/css-backgrounds-3/transition-updated-cr-2017-09.md", "tags": ["css","backgrounds","spec"], "category": "Specs"},
  {"title": "CSS Backgrounds 3 – radius expansion continuity", "url": "https://github.com/w3c/csswg-drafts/blob/main/css-backgrounds-3/radius-expansion-continuity.html", "tags": ["css","backgrounds","spec"], "category": "Specs"},
  {"title": "Example PR – Thesoulfit site", "url": "https://github.com/Dhruv-fullstack-dev/Thesoulfit.github.io/pull/2", "tags": ["github","pr","example"], "category": "Examples"},
  {"title": "Example PR – nguyenhuunghi portfolio", "url": "https://github.com/nguyenhuunghi/portfolio/pull/1", "tags": ["github","pr","example"], "category": "Examples"},
  {"title": "email-bugs – issues (index)", "url": "https://github.com/hteumeuleu/email-bugs/issues", "tags": ["email","bugs"], "category": "Email resources"},
  {"title": "email-bugs – issues page 2", "url": "https://github.com/hteumeuleu/email-bugs/issues?page=2", "tags": ["email","bugs"], "category": "Email resources"},
  {"title": "email-bugs – issues page 3", "url": "https://github.com/hteumeuleu/email-bugs/issues?page=3", "tags": ["email","bugs"], "category": "Email resources"},
  {"title": "email-bugs – issues page 4", "url": "https://github.com/hteumeuleu/email-bugs/issues?page=4", "tags": ["email","bugs"], "category": "Email resources"},
  {"title": "email-bugs – issues page 5", "url": "https://github.com/hteumeuleu/email-bugs/issues?page=5", "tags": ["email","bugs"], "category": "Email resources"},
  {"title": "LT Email Module Library (gh-pages)", "url": "https://github.com/lt-email-dev/lt-email-module-library/tree/gh-pages", "tags": ["email","modules"], "category": "Email resources"},
  {"title": "LT Email – index.md", "url": "https://github.com/lt-email-dev/lt-email-module-library/blob/gh-pages/index.md", "tags": ["email","docs"], "category": "Email resources"},
  {"title": "LT Email – dark-mode.md", "url": "https://github.com/lt-email-dev/lt-email-module-library/blob/gh-pages/dark-mode.md", "tags": ["email","dark-mode"], "category": "Email resources"},
  {"title": "Email on Acid – Dark mode for email", "url": "https://www.emailonacid.com/blog/article/email-development/dark-mode-for-email/", "tags": ["email","dark-mode"], "category": "Email resources"},
  {"title": "Email on Acid – Email development blog", "url": "https://www.emailonacid.com/blog/email-development/", "tags": ["email","blog"], "category": "Email resources"},
  {"title": "Email on Acid – Code emails for Outlook", "url": "https://www.emailonacid.com/blog/article/email-development/how-to-code-emails-for-outlook/", "tags": ["email","outlook"], "category": "Email resources"},
  {"title": "Email on Acid – Mobile optimization & retina images", "url": "https://www.emailonacid.com/blog/article/email-development/mobile-optimization-retina-images-in-email/", "tags": ["email","images","mobile"], "category": "Email resources"},
  {"title": "Hteumeuleu – Fixing Gmail dark mode (blend modes)", "url": "https://www.hteumeuleu.com/2021/fixing-gmail-dark-mode-css-blend-modes/", "tags": ["email","gmail","dark-mode"], "category": "Email resources"},
  {"title": "Tuts+ – Fix Outlook dark mode problems", "url": "https://webdesign.tutsplus.com/how-to-fix-outlook-dark-mode-problems--cms-37718t", "tags": ["email","outlook","dark-mode"], "category": "Email resources"},
  {"title": "Dev.to – Dark mode in AMP for Email", "url": "https://dev.to/bdjang/exploring-dark-mode-in-amp-email-5gm7", "tags": ["email","amp","dark-mode"], "category": "Email resources"},
  {"title": "Good Email Code – picture", "url": "https://www.goodemailcode.com/email-enhancements/picture", "tags": ["email","images"], "category": "Email resources"},
  {"title": "Good Email Code – stop Gmail image popup", "url": "https://www.goodemailcode.com/email-enhancements/stop-gmail-image-popup", "tags": ["email","gmail","images"], "category": "Email resources"},
  {"title": "Good Email Code – CSS art", "url": "https://www.goodemailcode.com/email-enhancements/css-art", "tags": ["email","css"], "category": "Email resources"},
  {"title": "Good Email Code – CSS art (Outlook support)", "url": "https://www.goodemailcode.com/email-enhancements/css-art#mso-outlook-support", "tags": ["email","css","outlook"], "category": "Email resources"},
  {"title": "Parcel – shared email", "url": "https://parcel.io/e/f6ce2d2f-372c-459f-82af-42c01c4a8820", "tags": ["email","tool"], "category": "Tools"},
  {"title": "Envato – Fix borders in dark mode email", "url": "https://elements.envato.com/learn/fixing-problems-with-borders-in-dark-mode-email-design", "tags": ["email","dark-mode"], "category": "Email resources"},
  {"title": "HowToTarget.email", "url": "https://www.howtotarget.email", "tags": ["email","targeting"], "category": "Email resources"},
  {"title": "Smashing Magazine – Complete guide to HTML email", "url": "https://www.smashingmagazine.com/2021/04/complete-guide-html-email-templates-tools/?ref=emailresourc.es", "tags": ["email","guide"], "category": "Email resources"},
  {"title": "Campaign Monitor – CSS support", "url": "https://www.campaignmonitor.com/css/?ref=emailresourc.es", "tags": ["email","compat"], "category": "Email resources"},
  {"title": "Hteumeuleu – Outlook rendering engine", "url": "https://www.hteumeuleu.com/2020/outlook-rendering-engine/?ref=emailresourc.es", "tags": ["email","outlook"], "category": "Email resources"},
  {"title": "CM Engineering – Outlook-specific CSS (fix bugs)", "url": "https://cm.engineering/fixing-bugs-with-outlook-specific-css-f4b8ae5be4f4", "tags": ["email","outlook","css"], "category": "Email resources"},
  {"title": "Badsender – ESP HTML bugs", "url": "https://github.com/Badsender-com/esp-html-bugs?ref=emailresourc.es", "tags": ["email","bugs"], "category": "Email resources"},
  {"title": "Fluid Typography tool", "url": "https://fluid-typography.netlify.app/?ref=emailresourc.es", "tags": ["css","typography","tool"], "category": "Tools"},
  {"title": "Campaign Monitor – Coding HTML emails", "url": "https://www.campaignmonitor.com/dev-resources/guides/coding-html-emails/", "tags": ["email","guide"], "category": "Email resources"},
  {"title": "Campaign Monitor – Mobile guide", "url": "https://www.campaignmonitor.com/dev-resources/guides/mobile/", "tags": ["email","mobile","guide"], "category": "Email resources"},
  {"title": "Hteumeuleu – React/Outlook.com dark mode", "url": "https://www.hteumeuleu.com/2021/emails-react-outlook-com-dark-mode/?ref=emailresourc.es", "tags": ["email","dark-mode","outlook"], "category": "Email resources"},
  {"title": "Hteumeuleu – Background properties in VML", "url": "https://www.hteumeuleu.com/2021/background-properties-in-vml/", "tags": ["email","vml","outlook"], "category": "Email resources"},
  {"title": "Tuts+ – Fix buttons in dark mode email", "url": "https://webdesign.tutsplus.com/fixing-problems-with-buttons-in-dark-mode-email-design--cms-39411a?ref=emailresourc.es", "tags": ["email","dark-mode","buttons"], "category": "Email resources"},
  {"title": "Medium – Dark-mode friendly mailers", "url": "https://ruwanthisulanjali.medium.com/how-i-created-dark-mode-friendly-mailers-d40e15e2a5f5", "tags": ["email","dark-mode"], "category": "Email resources"},
  {"title": "Hteumeuleu – Fixing Gmail dark mode (blend modes) (ref)", "url": "https://www.hteumeuleu.com/2021/fixing-gmail-dark-mode-css-blend-modes/?ref=emailresourc.es", "tags": ["email","gmail","dark-mode"], "category": "Email resources"},
  {"title": "MailNinja – Email previewer", "url": "https://mailninja.co/email-previewer?ref=emailresourc.es", "tags": ["email","preview","tool"], "category": "Tools"},
  {"title": "W3C – CSS Images Level 4: conic-gradients", "url": "https://www.w3.org/TR/css-images-4/#conic-gradients", "tags": ["css","images","spec"], "category": "Specs"},
  {"title": "Bennett Feely – Image effects", "url": "https://bennettfeely.com/image-effects/", "tags": ["css","effects","tool"], "category": "Tools"},
  {"title": "CSS-Tricks – Basics of CSS blend modes", "url": "https://css-tricks.com/basics-css-blend-modes/", "tags": ["css","blend-modes","article"], "category": "Email resources"},
  {"title": "Bennett Feely – Gradients", "url": "https://bennettfeely.com/gradients/", "tags": ["css","gradients","tool"], "category": "Tools"}
]
